exceltoamx/__init__.py
exceltoamx-0.0.5.dist-info/LICENSE
exceltoamx-0.0.5.dist-info/METADATA
exceltoamx-0.0.5.dist-info/WHEEL
exceltoamx-0.0.5.dist-info/top_level.txt
exceltoamx-0.0.5.dist-info/RECORD
