Metadata-Version: 2.1
Name: exceltoamx
Version: 0.0.5
Summary: xlsx to amx dict list
Home-page: https://github.com/logantv/exceltoamx
Author: Logan Vaughn
License: UNKNOWN
Project-URL: Bug Tracker, https://github.com/logantv/exceltoamx/issues
Platform: UNKNOWN
Classifier: Programming Language :: Python :: 3
Classifier: License :: OSI Approved :: MIT License
Classifier: Operating System :: OS Independent
Requires-Python: >=3.6
Requires-Dist: tablib
